flacarray.libs/libFLAC-2db9b6dd.so.14.0.0
flacarray.libs/libgomp-a34b3233.so.1.0.0
flacarray-0.3.4.dist-info/RECORD
flacarray-0.3.4.dist-info/METADATA
flacarray-0.3.4.dist-info/entry_points.txt
flacarray-0.3.4.dist-info/WHEEL
flacarray/demo.py
flacarray/hdf5.py
flacarray/array.py
flacarray/zarr_load_v0.py
flacarray/utils.py
flacarray/decompress.py
flacarray/io_common.py
flacarray/zarr.py
flacarray/zarr_load_v1.py
flacarray/hdf5_utils.py
flacarray/libflacarray.cpython-311-x86_64-linux-gnu.so
flacarray/compress.py
flacarray/hdf5_load_v1.py
flacarray/hdf5_load_v0.py
flacarray/mpi.py
flacarray/__init__.py
flacarray/tests/hdf5.py
flacarray/tests/array.py
flacarray/tests/bindings.py
flacarray/tests/utils.py
flacarray/tests/runner.py
flacarray/tests/zarr.py
flacarray/tests/__init__.py
flacarray/scripts/benchmark.py
flacarray/scripts/__init__.py
